tec_cli/__init__.py
tec_cli/__main__.py
tec_cli/discover.py
tec_cli/read.py
tec_cli-0.5.0.dist-info/WHEEL
tec_cli-0.5.0.dist-info/entry_points.txt
tec_cli-0.5.0.dist-info/METADATA
tec_cli-0.5.0.dist-info/RECORD
